vpy/__init__.py
vpy/__main__.py
vpy/auto_complete.py
vpy/highlights.py
vpy/hints.py
vpy/interactive.py
VisualPy-1.0.1.dist-info/LICENSE
VisualPy-1.0.1.dist-info/METADATA
VisualPy-1.0.1.dist-info/WHEEL
VisualPy-1.0.1.dist-info/top_level.txt
VisualPy-1.0.1.dist-info/RECORD
