Metadata-Version: 2.1
Name: VisualPy
Version: 1.0.1
Summary: Cross-platform python interpreter with highlighting, autocompletion and code hints (Like IPython and BPython)
Home-page: https://github.com/NIKDISSV-Forever/VisualPy
Author: NIKDISSV (Nikita)
Author-email: nikdissv@proton.me
License: MIT
Keywords: ipython,bpython,vpython,highlight,interpreter,interactive,code,console
Platform: UNKNOWN
Classifier: Development Status :: 4 - Beta
Classifier: Environment :: Console
Classifier: Intended Audience :: Developers
Classifier: Intended Audience :: System Administrators
Classifier: License :: OSI Approved
Classifier: License :: OSI Approved :: MIT License
Classifier: Operating System :: OS Independent
Classifier: Programming Language :: Python :: Implementation :: CPython
Classifier: Programming Language :: Python :: Implementation :: PyPy
Classifier: Topic :: Software Development :: Interpreters
Classifier: Topic :: Terminals
Classifier: Topic :: Text Editors
Classifier: Typing :: Typed
Requires-Python: >=3.8
License-File: LICENSE
Requires-Dist: pygments
Requires-Dist: rich
Requires-Dist: pyperclip
Requires-Dist: readchar
